dbviz/__init__.py
dbviz/data.py
dbviz/plot.py
dbviz/utils.py
dbviz-0.1.3.dist-info/licenses/LICENSE
dbviz-0.1.3.dist-info/METADATA
dbviz-0.1.3.dist-info/WHEEL
dbviz-0.1.3.dist-info/top_level.txt
dbviz-0.1.3.dist-info/RECORD
