Metadata-Version: 2.4
Name: dbviz
Version: 0.1.3
Summary: Decision Boundary Visualization for PyTorch Models
Requires-Python: >=3.12
License-File: LICENSE
Requires-Dist: matplotlib>=3.10.6
Requires-Dist: numpy>=1.26
Requires-Dist: torch>=2.8.0
Dynamic: license-file
